gfxds-0.1.0.dist-info/METADATA
gfxds-0.1.0.dist-info/WHEEL
gfxds-0.1.0.dist-info/licenses/LICENSE
gfxds/__init__.py
gfxds/__init__.pyi
gfxds/gfxds.cpython-39-x86_64-linux-gnu.so
gfxds/py.typed
gfxds-0.1.0.dist-info/RECORD
