Metadata-Version: 2.4
Name: gfxds
Version: 0.1.0
Classifier: Development Status :: 3 - Alpha
Classifier: Programming Language :: Rust
Requires-Dist: numpy>=1.21
License-File: LICENSE
Summary: Dataloaders for multi-channel graphics datasets
Author-email: Sam Sartor <me@samsartor.com>
License-Expression: MIT
Requires-Python: >=3.8
Project-URL: Homepage, https://github.com/samsartor/gfxds
Project-URL: Repository, https://github.com/samsartor/gfxds
